{
  "format_version": "1.16.100",
  "minecraft:item": {
    "description": {
      "identifier": "twilightforest:zombie_scepter",
      "category": "equipment"
    },
    "components": {
      "minecraft:creative_category": {
        "parent": "itemGroup.name.twilightforest.scepter"
      },
      "minecraft:display_name": {
        "value": "item.twilightforest.zombie_scepter"
      },
      "minecraft:icon": {
        "texture": "zombie_scepter"
      },
      "minecraft:max_stack_size": 1,
      "minecraft:hand_equipped": true,
      "minecraft:durability": {
        "max_durability": 9
      },
      "minecraft:on_use_on": {
        "on_use_on": {
          "event": "twilightforest:on_use_on"
        }
      },
      "minecraft:damage": 2,
      "minecraft:weapon": {
        "on_hurt_entity": {
          "event": "twilightforest:on_hurt_entity"
        }
      }
    },
    "events": {
      "twilightforest:on_use_on": {
        "sequence": [
          {
            "condition": "query.remaining_durability != 0",
            "damage": {
              "amount": 1,
              "target": "item",
              "type": "none"
            },
            "run_command": {
              "command": "summon twilightforest:loyal_zombie ~ ~ ~ twilightforest:from_scepter"
            }
          },
          {
            "condition": "query.remaining_durability == 0",
            "run_command": {
              "command": "tellraw @p {\"rawtext\":[{\"translate\":\"action.twilightforest.item.durability\",\"with\":{\"rawtext\":[{\"translate\":\"item.twilightforest.zombie_scepter\"}]}}]}"
            }
          }
        ]
      },
      "twilightforest:on_hurt_entity": {
        "sequence": [
          {
            "damage": {
              "amount": 0,
              "target": "item",
              "type": "none"
            }
          }
        ]
      }
    }
  }
}
