{
  "format_version": "1.10.0",
  "minecraft:attachable": {
    "description": {
      "identifier": "twilightforest:giant_sword",
      "materials": {
        "default": "entity_alphatest",
        "enchanted": "entity_alphatest_glint"
      },
      "textures": {
        "default": "textures/items/stone_sword",
        "enchanted": "textures/misc/enchanted_item_glint"
      },
      "geometry": {
        "default": "geometry.twilightforest.giant_sword"
      },
      "render_controllers": [ "controller.render.giant_sword" ]
    }
  }
}
