{
  "format_version": "1.16.100",
  "minecraft:item": {
    "description": {
      "identifier": "twilightforest:fiery_leggings",
      "category": "equipment"
    },
    "components": {
      "minecraft:creative_category": {
        "parent": "itemGroup.name.leggings"
      },
      "minecraft:display_name": {
        "value": "twilightforest.fiery_leggings.item"
      },
      "minecraft:icon": {
        "texture": "fiery_leggings"
      },
      "minecraft:enchantable" : {
        "value": 10,
        "slot": "armor_legs"
      },
      "minecraft:durability": {
        "max_durability": 375,
        "damage_chance": {
          "min": 60,
          "max": 100
        }
      },
      "minecraft:repairable": {
        "repair_items": [
          {
            "items": [
              "twilightforest:fiery_ingot"
            ],
            "repair_amount": "94"
          },
          {
            "items": [
              "twilightforest:fiery_leggings"
            ],
              "repair_amount": "context.other->query.remaining_durability + 19"
          }
        ]
      },
      "minecraft:armor": {
        "protection": 7
      },
      "minecraft:max_stack_size": 1,
      "minecraft:wearable": {
        "slot": "slot.armor.legs"
      }
    }
  }
}