{
  "format_version": "1.16.0",
  "minecraft:item": {
    "description": {
      "identifier": "twilightforest:fiery_ingot",
      "category": "items"
    },
    "components": {
      "minecraft:icon": {
        "texture": "fiery_ingot"
      },
      "minecraft:hover_text_color": "yellow",
      "minecraft:creative_category": {
        "parent": "itemGroup.name.twilightforest_items"
      },
      "minecraft:render_offsets": "miscellaneous",
      "minecraft:display_name": {
        "value": "twilightforest.fiery_ingot.item"
      }
    }
  }
}